polars_distance-0.5.3.dist-info/METADATA
polars_distance-0.5.3.dist-info/WHEEL
polars_distance/__init__.py
polars_distance/_internal.pyi
polars_distance/py.typed
polars_distance/_internal.abi3.so
polars_distance-0.5.3.dist-info/RECORD
