Metadata-Version: 2.4
Name: polars-distance
Version: 0.5.3
Classifier: Programming Language :: Rust
Classifier: Programming Language :: Python :: Implementation :: CPython
Classifier: Programming Language :: Python :: Implementation :: PyPy
Requires-Dist: polars>=0.20.16
Summary: Polars plugin for pairwise distance functions
Author-email: Ion Koutsours <15728914+ion-elgreco@users.noreply.github.com>
Requires-Python: >=3.8
Project-URL: Repository, https://github.com/ion-elgreco/polars-distance
Project-URL: Documentation, https://ion-elgreco.github.io/polars-distance/
Project-URL: Change Log, https://github.com/ion-elgreco/polars-distance/releases
Project-URL: Issue Tracker, https://github.com/ion-elgreco/polars-distance/issues
